avrodantic/__about__.py
avrodantic/__init__.py
avrodantic/cli.py
avrodantic/helper.py
avrodantic/parser.py
avrodantic/schemas.py
avrodantic-0.0.1.dist-info/METADATA
avrodantic-0.0.1.dist-info/WHEEL
avrodantic-0.0.1.dist-info/entry_points.txt
avrodantic-0.0.1.dist-info/licenses/LICENSE
avrodantic-0.0.1.dist-info/RECORD
